darca_embeddings/__init__.py
darca_embeddings/__version__.py
darca_embeddings/embedding.py
darca_embeddings-0.1.1.dist-info/LICENSE
darca_embeddings-0.1.1.dist-info/METADATA
darca_embeddings-0.1.1.dist-info/WHEEL
darca_embeddings-0.1.1.dist-info/RECORD
